fail_kit_lsp/__init__.py
fail_kit_lsp/analyzer.py
fail_kit_lsp/fixers.py
fail_kit_lsp/patterns.py
fail_kit_lsp/server.py
fail_kit_lsp-2.0.0.dist-info/METADATA
fail_kit_lsp-2.0.0.dist-info/WHEEL
fail_kit_lsp-2.0.0.dist-info/entry_points.txt
fail_kit_lsp-2.0.0.dist-info/RECORD
