Metadata-Version: 2.4
Name: fail-kit-lsp
Version: 2.0.0
Summary: F.A.I.L. Kit Language Server for Python - Forensic analysis for LangChain, CrewAI, and AutoGen
Project-URL: Homepage, https://github.com/resetroot99/The-FAIL-Kit
Project-URL: Documentation, https://github.com/resetroot99/The-FAIL-Kit/tree/main/python-lsp
Project-URL: Repository, https://github.com/resetroot99/The-FAIL-Kit
Author: F.A.I.L. Kit Team
License-Expression: MIT
Keywords: ai-safety,audit,autogen,crewai,fail-kit,forensic,langchain,language-server,lsp
Classifier: Development Status :: 4 - Beta
Classifier: Intended Audience :: Developers
Classifier: License :: OSI Approved :: MIT License
Classifier: Programming Language :: Python :: 3
Classifier: Programming Language :: Python :: 3.9
Classifier: Programming Language :: Python :: 3.10
Classifier: Programming Language :: Python :: 3.11
Classifier: Programming Language :: Python :: 3.12
Classifier: Topic :: Software Development :: Quality Assurance
Requires-Python: >=3.9
Requires-Dist: lsprotocol>=2023.0.0
Requires-Dist: pygls>=1.2.0
Provides-Extra: dev
Requires-Dist: black>=23.0; extra == 'dev'
Requires-Dist: mypy>=1.0; extra == 'dev'
Requires-Dist: pytest-cov>=4.0; extra == 'dev'
Requires-Dist: pytest>=7.0; extra == 'dev'
Requires-Dist: ruff>=0.1.0; extra == 'dev'
